RAISING/FeatureImp.py
RAISING/RSLM_implement.py
RAISING/__init__.py
RAISING/hp_tune_select.py
RAISING/static_function.py
RAISING-1.0.1.dist-info/LICENSE
RAISING-1.0.1.dist-info/METADATA
RAISING-1.0.1.dist-info/WHEEL
RAISING-1.0.1.dist-info/top_level.txt
RAISING-1.0.1.dist-info/RECORD
