Metadata-Version: 2.1
Name: RAISING
Version: 1.0.1
Summary: RAISING: A supervised deep learning framework for hyperparameter tuning and feature selection
Author: Devashish Tripathi
Author-email: devashishtripathi697@gmail.com
License: GPL-3.0-or-later
Classifier: Programming Language :: Python :: 3
Classifier: License :: OSI Approved :: GNU General Public License v3 (GPLv3)
Classifier: Operating System :: OS Independent
Requires-Python: >=3.9
License-File: LICENSE
Requires-Dist: pandas>=1.5.2
Requires-Dist: numpy>=1.23.5
Requires-Dist: tensorflow<2.16.0
Requires-Dist: keras>=2.11.0
Requires-Dist: scikit-learn>=1.0.2
Requires-Dist: keras-tuner>=1.1.3
Requires-Dist: pysnptools>=0.5.10
Requires-Dist: tensorflow_addons>=0.18.0
Requires-Dist: imbalanced-learn>=0.11.0
Requires-Dist: shap>=0.41.0
Requires-Dist: statsmodels>=0.14.0
Requires-Dist: matplotlib>=3.6.2
